lpjguess_runner/__init__.py
lpjguess_runner/_loader.py
lpjguess_runner/rids/win-x64/ExtendedXmlSerializer.dll
lpjguess_runner/rids/win-x64/LightInject.dll
lpjguess_runner/rids/win-x64/LpjGuess.Core.dll
lpjguess_runner/rids/win-x64/LpjGuess.Core.pdb
lpjguess_runner/rids/win-x64/LpjGuess.Core.xml
lpjguess_runner/rids/win-x64/LpjGuess.Runner.deps.json
lpjguess_runner/rids/win-x64/LpjGuess.Runner.dll
lpjguess_runner/rids/win-x64/LpjGuess.Runner.pdb
lpjguess_runner/rids/win-x64/LpjGuess.Runner.xml
lpjguess_runner/rids/win-x64/Microsoft.Extensions.Configuration.Abstractions.dll
lpjguess_runner/rids/win-x64/Microsoft.Extensions.Configuration.Binder.dll
lpjguess_runner/rids/win-x64/Microsoft.Extensions.Configuration.dll
lpjguess_runner/rids/win-x64/Microsoft.Extensions.DependencyInjection.Abstractions.dll
lpjguess_runner/rids/win-x64/Microsoft.Extensions.DependencyInjection.dll
lpjguess_runner/rids/win-x64/Microsoft.Extensions.Logging.Abstractions.dll
lpjguess_runner/rids/win-x64/Microsoft.Extensions.Logging.Configuration.dll
lpjguess_runner/rids/win-x64/Microsoft.Extensions.Logging.Console.dll
lpjguess_runner/rids/win-x64/Microsoft.Extensions.Logging.dll
lpjguess_runner/rids/win-x64/Microsoft.Extensions.Options.ConfigurationExtensions.dll
lpjguess_runner/rids/win-x64/Microsoft.Extensions.Options.dll
lpjguess_runner/rids/win-x64/Microsoft.Extensions.Primitives.dll
lpjguess_runner/rids/win-x64/NReco.LambdaParser.dll
lpjguess_runner/rids/win-x64/Newtonsoft.Json.dll
lpjguess_runner/rids/win-x64/Sprache.dll
lpjguess_runner-1.0.3.dist-info/METADATA
lpjguess_runner-1.0.3.dist-info/WHEEL
lpjguess_runner-1.0.3.dist-info/top_level.txt
lpjguess_runner-1.0.3.dist-info/RECORD
