Metadata-Version: 2.4
Name: lpjguess-runner
Version: 1.0.3
Summary: Python wrapper for LPJ-Guess experiment runner (via pythonnet + .NET 9)
Author-email: Drew Holzworth <d.holzworth@westernsydney.edu.au>
License-Expression: MIT
Project-URL: Homepage, https://github.com/hie-dave/lpjg-gui
Project-URL: Source, https://github.com/hie-dave/lpjg-gui
Project-URL: Issues, https://github.com/hie-dave/lpjg-gui/issues
Keywords: LPJ-Guess,dynamic,vegetation,model,DGVM,ecosystem,simulation,experiments
Classifier: Programming Language :: Python :: 3
Classifier: Operating System :: POSIX :: Linux
Classifier: Operating System :: Microsoft :: Windows
Classifier: Operating System :: MacOS
Requires-Python: <3.14,>=3.10
Requires-Dist: pythonnet>=3.0.1
